mydatapy/__init__.py
mydatapy/client.py
mydatapy/models/invoice.py
mydatapy/templates/__init__.py
mydatapy/templates/invoice.xml
mydatapy-0.1.1.dist-info/WHEEL
mydatapy-0.1.1.dist-info/METADATA
mydatapy-0.1.1.dist-info/RECORD
